azure/kusto/ingest/__init__.py
azure/kusto/ingest/_ingest_telemetry.py
azure/kusto/ingest/_ranked_storage_account.py
azure/kusto/ingest/_resource_manager.py
azure/kusto/ingest/_status_q.py
azure/kusto/ingest/_storage_account_set.py
azure/kusto/ingest/_stream_extensions.py
azure/kusto/ingest/_version.py
azure/kusto/ingest/base_ingest_client.py
azure/kusto/ingest/descriptors.py
azure/kusto/ingest/exceptions.py
azure/kusto/ingest/ingest_client.py
azure/kusto/ingest/ingestion_blob_info.py
azure/kusto/ingest/ingestion_properties.py
azure/kusto/ingest/managed_streaming_ingest_client.py
azure/kusto/ingest/py.typed
azure/kusto/ingest/status.py
azure/kusto/ingest/streaming_ingest_client.py
azure_kusto_ingest-6.0.1.dist-info/WHEEL
azure_kusto_ingest-6.0.1.dist-info/METADATA
azure_kusto_ingest-6.0.1.dist-info/RECORD
