Metadata-Version: 2.4
Name: azure-kusto-ingest
Version: 6.0.1
Summary: Kusto Ingest Client
Keywords: azure,kusto,ingest,data,analytics
Author: Microsoft Corporation
Author-email: Microsoft Corporation <kustalk@microsoft.com>
License-Expression: MIT
Classifier: Programming Language :: Python
Classifier: Programming Language :: Python :: 3.9
Classifier: Programming Language :: Python :: 3.10
Classifier: Programming Language :: Python :: 3.11
Classifier: Programming Language :: Python :: 3.12
Classifier: Programming Language :: Python :: 3.13
Classifier: License :: OSI Approved :: MIT License
Requires-Dist: azure-kusto-data
Requires-Dist: azure-storage-blob==12.26.0
Requires-Dist: azure-storage-queue==12.13.0
Requires-Dist: tenacity>=9.1.2
Requires-Dist: pandas>=2.3.1 ; extra == 'pandas'
Requires-Python: >=3.9
Project-URL: Repository, https://github.com/Azure/azure-kusto-python
Provides-Extra: aio
Provides-Extra: pandas
